seesaw/__init__.py
seesaw/config.py
seesaw/event.py
seesaw/externalprocess.py
seesaw/externalprocess_test.py
seesaw/init_test.py
seesaw/item.py
seesaw/item_test.py
seesaw/log.py
seesaw/pipeline.py
seesaw/pipeline_test.py
seesaw/project.py
seesaw/runner.py
seesaw/runner_test.py
seesaw/six.py
seesaw/task.py
seesaw/test_base.py
seesaw/tracker.py
seesaw/util.py
seesaw/util_test.py
seesaw/warrior.py
seesaw/web.py
seesaw/web_util.py
seesaw/public/index.html
seesaw/public/jquery-1.12.4.min.js
seesaw/public/reset.css
seesaw/public/script.js
seesaw/public/smoothie.js
seesaw/public/sockjs-0.3.js
seesaw/public/style.css
seesaw/public/warrior-logo.png
seesaw/script/__init__.py
seesaw/script/run_pipeline.py
seesaw/script/run_warrior.py
seesaw/templates/all-projects.html
seesaw/templates/help.html
seesaw/templates/settings.html
seesaw2-0.10.3.data/scripts/run-pipeline3
seesaw2-0.10.3.data/scripts/run-warrior3
seesaw2-0.10.3.dist-info/LICENSE.txt
seesaw2-0.10.3.dist-info/METADATA
seesaw2-0.10.3.dist-info/WHEEL
seesaw2-0.10.3.dist-info/top_level.txt
seesaw2-0.10.3.dist-info/RECORD
