Metadata-Version: 2.1
Name: seesaw2
Version: 0.10.3
Summary: ArchiveTeam seesaw kit
Home-page: http://www.archiveteam.org/
Maintainer: ArchiveTeam
Maintainer-email: warrior@archiveteam.org
License: UNKNOWN
Platform: UNKNOWN
License-File: LICENSE.txt
Requires-Dist: Tornado (<5.99999.99999,>=4)
Requires-Dist: sockjs-tornado
